{"status":"succeeded","result":{"position_id":"1160","user_id":"0","status":"n","company":"Finix","title":"Backend Engineer (Must have Java, 3+ yr exp) \/ Engineering Manager \/ PM \/ DevOp \/ UX","description":null,"country":"US","location":"SF \/ San Jose","link":"https:\/\/learn.finixpayments.com\/jobs","referer":"Yuyi Li","internal":"0","email":"yuyi@finixpayments.com","phone":null,"notes":"Payment startp up. Top tier VC. HM said no new grad and junior at the moment","date_posted":"2020-05-08"}}