{"status":"succeeded","result":{"position_id":"879","user_id":"0","status":"n","company":"Alibaba\uff08\u6dd8\u7cfb\u6280\u672f\uff09","title":"\u6570\u636e\u5206\u6790\u4e13\u5bb6\uff08P7&P8\uff09","description":null,"country":"China","location":"\u676d\u5dde\uff08\u6700\u7a33\u5065\u5b9c\u5c45\u7684\u65b0\u4e00\u7ebf\u57ce\u5e02\uff09","link":"","referer":"Wenxi Zhang","internal":"0","email":"heyi.zwx@alibaba-inc.com","phone":null,"notes":"\u6570\u636e\u5206\u6790","date_posted":"2020-05-13"}}